istr/LICENSE.txt
istr/__init__.py
istr/istr.py
istr_python-1.1.12.dist-info/METADATA
istr_python-1.1.12.dist-info/WHEEL
istr_python-1.1.12.dist-info/top_level.txt
istr_python-1.1.12.dist-info/RECORD
