Metadata-Version: 2.4
Name: istr-python
Version: 1.1.12
Summary: istr - strings you can count on
Author-email: Ruud van der Ham <rt.van.der.ham@gmail.com>
Project-URL: Homepage, https://github.com/salabim/istr
Project-URL: Repository, https://github.com/salabim/istr
Classifier: Development Status :: 5 - Production/Stable
Classifier: License :: OSI Approved :: MIT License
Classifier: Programming Language :: Python :: 3 :: Only
Requires-Python: >=3.8
